auth0-stubs/METADATA.toml
auth0-stubs/__init__.pyi
auth0-stubs/asyncify.pyi
auth0-stubs/exceptions.pyi
auth0-stubs/py.typed
auth0-stubs/rest.pyi
auth0-stubs/rest_async.pyi
auth0-stubs/types.pyi
auth0-stubs/utils.pyi
auth0-stubs/authentication/__init__.pyi
auth0-stubs/authentication/async_token_verifier.pyi
auth0-stubs/authentication/back_channel_login.pyi
auth0-stubs/authentication/base.pyi
auth0-stubs/authentication/client_authentication.pyi
auth0-stubs/authentication/database.pyi
auth0-stubs/authentication/delegated.pyi
auth0-stubs/authentication/enterprise.pyi
auth0-stubs/authentication/get_token.pyi
auth0-stubs/authentication/passwordless.pyi
auth0-stubs/authentication/pushed_authorization_requests.pyi
auth0-stubs/authentication/revoke_token.pyi
auth0-stubs/authentication/social.pyi
auth0-stubs/authentication/token_verifier.pyi
auth0-stubs/authentication/users.pyi
auth0-stubs/management/__init__.pyi
auth0-stubs/management/actions.pyi
auth0-stubs/management/async_auth0.pyi
auth0-stubs/management/attack_protection.pyi
auth0-stubs/management/auth0.pyi
auth0-stubs/management/blacklists.pyi
auth0-stubs/management/branding.pyi
auth0-stubs/management/client_credentials.pyi
auth0-stubs/management/client_grants.pyi
auth0-stubs/management/clients.pyi
auth0-stubs/management/connections.pyi
auth0-stubs/management/custom_domains.pyi
auth0-stubs/management/device_credentials.pyi
auth0-stubs/management/email_templates.pyi
auth0-stubs/management/emails.pyi
auth0-stubs/management/grants.pyi
auth0-stubs/management/guardian.pyi
auth0-stubs/management/hooks.pyi
auth0-stubs/management/jobs.pyi
auth0-stubs/management/log_streams.pyi
auth0-stubs/management/logs.pyi
auth0-stubs/management/organizations.pyi
auth0-stubs/management/prompts.pyi
auth0-stubs/management/resource_servers.pyi
auth0-stubs/management/roles.pyi
auth0-stubs/management/rules.pyi
auth0-stubs/management/rules_configs.pyi
auth0-stubs/management/self_service_profiles.pyi
auth0-stubs/management/stats.pyi
types_auth0_python-4.10.0.20250822.dist-info/licenses/LICENSE
types_auth0_python-4.10.0.20250822.dist-info/METADATA
types_auth0_python-4.10.0.20250822.dist-info/WHEEL
types_auth0_python-4.10.0.20250822.dist-info/top_level.txt
types_auth0_python-4.10.0.20250822.dist-info/RECORD
